[{"name": "01 Jacqueline (2018_06_06 22_10_32 UTC).mp3"}, {"name": "02 Tell Her Tonight (2018_06_06 22_10_32 UTC).mp3"}, {"name": "03 Take Me Out (2018_06_06 22_10_32 UTC).mp3"}, {"name": "04 The Dark of the Matinee (2018_06_06 22_10_32 UTC).mp3"}, {"name": "05 Auf Achse (2018_06_06 22_10_32 UTC).mp3"}, {"name": "06 Cheating On You (2018_06_06 22_10_32 UTC).mp3"}, {"name": "07 This Fire (2018_06_06 22_10_32 UTC).mp3"}, {"name": "08 Darts of Pleasure (2018_06_06 22_10_32 UTC).mp3"}, {"name": "09 Michael (2018_06_06 22_10_32 UTC).mp3"}, {"name": "10 Come On Home (2018_06_06 22_10_32 UTC).mp3"}, {"name": "11 40' (2018_06_06 22_10_32 UTC).mp3"}, {"name": "AlbumArtSmall (2018_06_06 22_10_32 UTC).jpg"}, {"name": "AlbumArtSmall (2019_04_15 23_01_08 UTC).jpg"}, {"name": "AlbumArt_{5ED6F754-C11B-4040-8BDA-59361F4FD633}_Large (2018_06_06 22_10_32 UTC).jpg"}, {"name": "AlbumArt_{5ED6F754-C11B-4040-8BDA-59361F4FD633}_Small (2018_06_06 22_10_32 UTC).jpg"}, {"name": "AlbumArt_{B5020207-474E-4720-DADF-592DDF3D1E00}_Large (2019_04_15 23_01_08 UTC).jpg"}, {"name": "AlbumArt_{B5020207-474E-4720-DADF-592DDF3D1E00}_Small (2019_04_15 23_01_08 UTC).jpg"}, {"name": "Folder (2018_06_06 22_10_32 UTC).jpg"}, {"name": "Folder (2019_04_15 23_01_08 UTC).jpg"}, {"name": "cover.jpg"}, {"name": "desktop (2018_06_06 22_10_32 UTC).ini"}]