[{"name": "01 K.I. Feeling (2018_06_06 22_10_32 UTC).mp3"}, {"name": "02 The Way U Move (2018_06_06 22_10_32 UTC).mp3"}, {"name": "03 Controlling Transmission (2018_06_06 22_10_32 UTC).mp3"}, {"name": "04 Oh Yeah (2018_06_06 22_10_32 UTC).mp3"}, {"name": "05 It's A Jungle (2018_06_06 22_10_32 UTC).mp3"}, {"name": "06 Do It Now! (2018_06_06 22_10_32 UTC).mp3"}, {"name": "07 Full-Bore (2018_06_06 22_10_32 UTC).mp3"}, {"name": "08 The Instinct (2018_06_06 22_10_32 UTC).mp3"}, {"name": "09 Yo Check This Out! (2018_06_06 22_10_32 UTC).mp3"}, {"name": "10 Freeze (2018_06_06 22_10_32 UTC).mp3"}, {"name": "11 Trailblazer (2018_06_06 22_10_32 UTC).mp3"}, {"name": "12 Tooth & Claw (2018_06_06 22_10_32 UTC).mp3"}, {"name": "13 Ya Ha Haa (2018_06_06 22_10_32 UTC).mp3"}, {"name": "14 Rumble (2018_06_06 22_10_32 UTC).mp3"}, {"name": "15 The Extreme (2018_06_06 22_10_32 UTC).mp3"}, {"name": "30 Humiliation (2018_06_06 22_10_32 UTC).mp3"}, {"name": "AlbumArtSmall (2018_06_06 22_10_32 UTC).jpg"}, {"name": "AlbumArtSmall (2019_04_15 22_00_03 UTC).jpg"}, {"name": "AlbumArtSmall (2019_04_16 05_03_24 UTC).jpg"}, {"name": "AlbumArt_{B5020207-474E-4720-59D0-CF2E263BEB00}_Large (2019_04_16 05_03_24 UTC).jpg"}, {"name": "AlbumArt_{B5020207-474E-4720-59D0-CF2E263BEB00}_Small (2019_04_16 05_03_24 UTC).jpg"}, {"name": "Folder (2018_06_06 22_10_32 UTC).jpg"}, {"name": "Folder (2019_04_15 22_00_03 UTC).jpg"}, {"name": "Folder (2019_04_16 05_03_24 UTC).jpg"}]